cacheback2/__init__.py
cacheback2/cache_back.py
cacheback2/cli.py
cacheback2/dependency.py
cacheback2/headers.py
cacheback2-0.0.70.dist-info/METADATA
cacheback2-0.0.70.dist-info/WHEEL
cacheback2-0.0.70.dist-info/top_level.txt
cacheback2-0.0.70.dist-info/RECORD
