Metadata-Version: 2.1
Name: cacheback2
Version: 0.0.70
Summary: UNKNOWN
Home-page: UNKNOWN
Author: jeein
Author-email: 
License: MIT
Platform: UNKNOWN
Requires-Dist: SQLAlchemy (==1.4.45)
Requires-Dist: numpy (==1.23.5)
Requires-Dist: pandas (==1.5.2)
Requires-Dist: psycopg2-binary (==2.9.3)
Requires-Dist: wheel (==0.38.4)
Requires-Dist: jupytext
